.gitignore
CHANGES.rst
LICENSE
README.rst
setup.cfg
setup.py
tox.ini
bulby/__init__.py
bulby/client.py
bulby/color.py
bulby/models.py
bulby/ssdp.py
bulby.egg-info/PKG-INFO
bulby.egg-info/SOURCES.txt
bulby.egg-info/dependency_links.txt
bulby.egg-info/entry_points.txt
bulby.egg-info/requires.txt
bulby.egg-info/top_level.txt
requirements/install.txt
requirements/test.txt
tests/test_client.py
tests/test_color.py