Metadata-Version: 1.1
Name: bulby
Version: 0.0.1.dev0
Summary: Manages the phillips hue lightbulbs
Home-page: https://github.com/sontek/bulby.git
Author: John Anderson
Author-email: sontek@gmail.com
License: MIT
Keywords: etl extract transform load
Platform: UNKNOWN
Classifier: Development Status :: 5 - Production/Stable
Classifier: Intended Audience :: Developers
Classifier: Programming Language :: Python :: 3
Classifier: Programming Language :: Python :: 3.4
